Metadata-Version: 2.1
Name: ngramso
Version: 1.0.0
Summary: Making Ngram Analysis from Stack Overflow Questions Dataframe
Author-email: bakircius <burakbakirci@gmail.com>
License:                     GNU GENERAL PUBLIC LICENSE
Project-URL: Homepage, https://github.com/bakircius/ngramso
Project-URL: Issues, https://github.com/bakircius/ngramso/issues
Project-URL: Repository, https://github.com/bakircius/ngramso.git
Classifier: Programming Language :: Python :: 3
Classifier: License :: OSI Approved :: MIT License
Classifier: Operating System :: OS Independent
Requires-Python: >=3.8
License-File: LICENSE
Requires-Dist: requests
Requires-Dist: pandas
Requires-Dist: numpy
Requires-Dist: sosq
Requires-Dist: emek
